MANIFEST.in
README.rst
setup.py
spa/__init__.py
spa/app.py
spa/exceptions.py
spa/gzip_util.py
spa/handler.py
spa/homepage.py
spa/jwtcookie.py
spa/middlewares.py
spa/utils.py
spa/version.txt
spa/wrappers.py
spa.egg-info/PKG-INFO
spa.egg-info/SOURCES.txt
spa.egg-info/dependency_links.txt
spa.egg-info/requires.txt
spa.egg-info/top_level.txt
spa/static/__init__.py
spa/static/handlers.py
spa/static/smart.py
test/test_app.py
test/test_csrf.py
test/test_homepage.py
test/test_session.py
test/test_static.py
test/test_websocket.py