Metadata-Version: 1.0
Name: spa
Version: 0.10.0
Summary: A Python micro framework for REST APIs and single-page-applications.
Home-page: UNKNOWN
Author: Brent Tubbs
Author-email: brent.tubbs@gmail.com
License: UNKNOWN
Platform: UNKNOWN
